README.rst
setup.py
BdMusic/BaiduMusic.py
BdMusic/BaiduMusicUtils.py
BdMusic/__init__.py
BdMusic/download.py
BdMusic/player.py
BdMusic.egg-info/PKG-INFO
BdMusic.egg-info/SOURCES.txt
BdMusic.egg-info/dependency_links.txt
BdMusic.egg-info/entry_points.txt
BdMusic.egg-info/not-zip-safe
BdMusic.egg-info/requires.txt
BdMusic.egg-info/top_level.txt